streamlit_timing/__init__.py
streamlit_timing/eventloop.py
streamlit_timing/session_info.py
streamlit_timing-0.1.0.dist-info/LICENSE
streamlit_timing-0.1.0.dist-info/WHEEL
streamlit_timing-0.1.0.dist-info/METADATA
streamlit_timing-0.1.0.dist-info/RECORD
